{
  "$id": "https://www.itb.ec.europa.eu/api/unlinkShared_request",
  "$schema": "http://json-schema.org/draft-07/schema#",
  "description": "JSON schema for the test suites' unlinkShared operation request payload",
  "type": "object",
  "properties": {
    "testSuite": {
      "description": "The identifier of the shared test suite.",
      "type": "string"
    },
    "specifications": {
      "description": "The list of specifications to unlink from the test suite (identified via their API keys).",
      "type": "array",
      "items": {
        "type": "string"
      }
    }
  },
  "required": [
    "testSuite",
    "specifications"
  ],
  "additionalProperties": false
}